{
    "resetFormOnClick": false,
    "boxShadow": "none",
    "mobileBottomRow": 22,
    "widgetName": "btn_property_submit",
    "onClick": "{{Insert_property_relation.run().then(() => {\n  resetWidget(\"new_property_modal\", true);\n}).catch(() => {\n  showAlert('House already exists', 'error');\n});}}",
    "buttonColor": "{{appsmith.theme.colors.primaryColor}}",
    "displayName": "Button",
    "iconSVG": "https://appcdn.appsmith.com/static/media/icon.05d209fafeb13a8569e3b4e97069d9ee.svg",
    "searchTags": [
        "click",
        "submit"
    ],
    "topRow": 18,
    "bottomRow": 22,
    "type": "BUTTON_WIDGET",
    "hideCard": false,
    "mobileRightColumn": 63,
    "animateLoading": true,
    "dynamicTriggerPathList": [{"key": "onClick"}],
    "leftColumn": 50,
    "dynamicBindingPathList": [
        {"key": "buttonColor"},
        {"key": "borderRadius"}
    ],
    "text": "Submit",
    "isDisabled": false,
    "key": "qi8hlqn3tf",
    "isDeprecated": false,
    "rightColumn": 64,
    "isDefaultClickDisabled": true,
    "widgetId": "lpxdgg77kr",
    "buttonStyle": "PRIMARY_BUTTON",
    "minWidth": 120,
    "isVisible": true,
    "recaptchaType": "V3",
    "version": 1,
    "parentId": "14davuln16",
    "tags": ["Buttons"],
    "renderMode": "CANVAS",
    "isLoading": false,
    "mobileTopRow": 18,
    "responsiveBehavior": "hug",
    "originalTopRow": 18,
    "disabledWhenInvalid": false,
    "borderRadius": "{{appsmith.theme.borderRadius.appBorderRadius}}",
    "mobileLeftColumn": 47,
    "originalBottomRow": 22,
    "buttonVariant": "PRIMARY",
    "placement": "CENTER"
}